mertisreader/__init__.py
mertisreader/_modidx.py
mertisreader/_nbdev.py
mertisreader/core.py
mertisreader-0.0.3.dist-info/licenses/LICENSE
nbdev_template/__init__.py
nbdev_template/_nbdev.py
nbdev_template/core.py
mertisreader-0.0.3.dist-info/METADATA
mertisreader-0.0.3.dist-info/WHEEL
mertisreader-0.0.3.dist-info/top_level.txt
mertisreader-0.0.3.dist-info/RECORD
